cefpython3/LICENSE.txt
cefpython3/License
cefpython3/README.txt
cefpython3/__init__.py
cefpython3/cef.pak
cefpython3/cef_100_percent.pak
cefpython3/cef_200_percent.pak
cefpython3/cef_extensions.pak
cefpython3/cefpython_py27.pyd
cefpython3/cefpython_py34.pyd
cefpython3/cefpython_py35.pyd
cefpython3/cefpython_py36.pyd
cefpython3/cefpython_py37.pyd
cefpython3/cefpython_py38.pyd
cefpython3/cefpython_py39.pyd
cefpython3/chrome_elf.dll
cefpython3/d3dcompiler_43.dll
cefpython3/d3dcompiler_47.dll
cefpython3/debug.log
cefpython3/devtools_resources.pak
cefpython3/icudtl.dat
cefpython3/libEGL.dll
cefpython3/libGLESv2.dll
cefpython3/libcef.dll
cefpython3/msvcp100.dll
cefpython3/msvcp140.dll
cefpython3/msvcp90.dll
cefpython3/natives_blob.bin
cefpython3/snapshot_blob.bin
cefpython3/subprocess.exe
cefpython3/v8_context_snapshot.bin
cefpython3/widevinecdmadapter.dll
cefpython3/examples/README-examples.md
cefpython3/examples/debug.log
cefpython3/examples/gtk2.py
cefpython3/examples/gtk3.py
cefpython3/examples/hello_world.py
cefpython3/examples/pysdl2.py
cefpython3/examples/pywin32.py
cefpython3/examples/qt.py
cefpython3/examples/screenshot.png
cefpython3/examples/screenshot.py
cefpython3/examples/tkinter_.py
cefpython3/examples/tutorial.py
cefpython3/examples/wxpython.py
cefpython3/examples/pyinstaller/README-pyinstaller.md
cefpython3/examples/pyinstaller/hook-cefpython3.py
cefpython3/examples/pyinstaller/pyinstaller.py
cefpython3/examples/pyinstaller/pyinstaller.spec
cefpython3/examples/pyinstaller/screenshots/cefapp_directory.jpg
cefpython3/examples/pyinstaller/screenshots/cefapp_fatal_error.jpg
cefpython3/examples/resources/back.gif
cefpython3/examples/resources/back.png
cefpython3/examples/resources/chromium.ico
cefpython3/examples/resources/forward.gif
cefpython3/examples/resources/forward.png
cefpython3/examples/resources/gtk.png
cefpython3/examples/resources/pyqt4.png
cefpython3/examples/resources/pyqt5.png
cefpython3/examples/resources/pyside.png
cefpython3-66.1.dist-info/METADATA
cefpython3-66.1.dist-info/WHEEL
cefpython3-66.1.dist-info/top_level.txt
cefpython3-66.1.dist-info/RECORD
